pytorchqbit/__init__.py
pytorchqbit/convert.py
pytorchqbit/gate.py
pytorchqbit/pauli_group.py
pytorchqbit/qbit.py
pytorchqbit/stabilizer.py
pytorchqbit-0.0.1.dist-info/LICENSE
pytorchqbit-0.0.1.dist-info/METADATA
pytorchqbit-0.0.1.dist-info/WHEEL
pytorchqbit-0.0.1.dist-info/top_level.txt
pytorchqbit-0.0.1.dist-info/RECORD
