Metadata-Version: 2.1
Name: pytorchqbit
Version: 0.0.1
Summary: Quantum bit and the usual gates in torch tensors straight from the Wikipedia
Home-page: https://github.com/kummahiih/pytorchqbit
Author: Pauli Rikula
License: MIT
Platform: UNKNOWN
Classifier: License :: OSI Approved :: MIT License
Classifier: Programming Language :: Python :: 3.6
Requires-Python: ~=3.10
License-File: LICENSE
Requires-Dist: torch (>=2.0.0)
